togomq/__init__.py
togomq/client.py
togomq/config.py
togomq/errors.py
togomq/logger.py
togomq/message.py
togomq/subscribe_options.py
togomq_sdk-0.1.3.dist-info/licenses/LICENSE
togomq_sdk-0.1.3.dist-info/METADATA
togomq_sdk-0.1.3.dist-info/WHEEL
togomq_sdk-0.1.3.dist-info/top_level.txt
togomq_sdk-0.1.3.dist-info/RECORD
