Metadata-Version: 2.4
Name: togomq-sdk
Version: 0.1.3
Summary: Official Python SDK for TogoMQ - a modern, high-performance message queue service
Home-page: https://github.com/TogoMQ/togomq-sdk-python
Author: TogoMQ
Author-email: TogoMQ <info@togomq.io>
License: MIT
Project-URL: Homepage, https://togomq.io
Project-URL: Documentation, https://togomq.io/docs
Project-URL: Repository, https://github.com/TogoMQ/togomq-sdk-python
Project-URL: Issues, https://github.com/TogoMQ/togomq-sdk-python/issues
Keywords: togomq,message-queue,grpc,pubsub,messaging
Classifier: Development Status :: 4 - Beta
Classifier: Intended Audience :: Developers
Classifier: License :: OSI Approved :: MIT License
Classifier: Programming Language :: Python :: 3
Classifier: Programming Language :: Python :: 3.9
Classifier: Programming Language :: Python :: 3.10
Classifier: Programming Language :: Python :: 3.11
Classifier: Programming Language :: Python :: 3.12
Classifier: Topic :: Software Development :: Libraries :: Python Modules
Classifier: Topic :: System :: Networking
Requires-Python: >=3.9
License-File: LICENSE
Requires-Dist: togomq-grpc>=0.1.11
Requires-Dist: grpcio>=1.60.0
Requires-Dist: protobuf>=4.25.0
Provides-Extra: dev
Requires-Dist: pytest>=7.4.0; extra == "dev"
Requires-Dist: pytest-asyncio>=0.21.0; extra == "dev"
Requires-Dist: pytest-cov>=4.1.0; extra == "dev"
Requires-Dist: black>=23.7.0; extra == "dev"
Requires-Dist: ruff>=0.0.285; extra == "dev"
Requires-Dist: mypy>=1.5.0; extra == "dev"
Dynamic: author
Dynamic: home-page
Dynamic: license-file
Dynamic: requires-python
